ai_service_python_sdk/__init__.py
ai_service_python_sdk/setup.py
ai_service_python_sdk/client/__init__.py
ai_service_python_sdk/client/api_client.py
ai_service_python_sdk/client/configuration.py
ai_service_python_sdk/client/rest.py
ai_service_python_sdk/client/api/__init__.py
ai_service_python_sdk/client/api/ai_service_ai_creation_api.py
ai_service_python_sdk/client/api/ai_service_aigc_images_api.py
ai_service_python_sdk/client/api/ai_service_image_api.py
ai_service_python_sdk/client/api/ai_service_job_api.py
ai_service_python_sdk/client/api/ai_service_llm_api.py
ai_service_python_sdk/client/api/ai_service_text_api.py
ai_service_python_sdk/client/api/ai_service_video_api.py
ai_service_python_sdk/client/models/__init__.py
ai_service_python_sdk/client/models/ai_creation_request.py
ai_service_python_sdk/client/models/aigc_check_request.py
ai_service_python_sdk/client/models/aigc_create_request.py
ai_service_python_sdk/client/models/aigc_sd_request.py
ai_service_python_sdk/client/models/aigc_train_request.py
ai_service_python_sdk/client/models/batch_video_request.py
ai_service_python_sdk/client/models/batch_video_request_videos.py
ai_service_python_sdk/client/models/image_request.py
ai_service_python_sdk/client/models/llm_eval_judger_request.py
ai_service_python_sdk/client/models/llm_eval_judger_request_messages.py
ai_service_python_sdk/client/models/response.py
ai_service_python_sdk/client/models/text_request.py
ai_service_python_sdk/client/models/video_request.py
ai_service_python_sdk/test/__init__.py
ai_service_python_sdk/test/test_ai_service_ai_creation_api.py
ai_service_python_sdk/test/test_ai_service_aigc_images_api.py
ai_service_python_sdk/test/test_ai_service_image_api.py
ai_service_python_sdk/test/test_ai_service_job_api.py
ai_service_python_sdk/test/test_ai_service_text_api.py
ai_service_python_sdk/test/test_ai_service_video_api.py
ai_service_python_sdk/test/test_llm_eval_judger_request.py
ai_service_python_sdk/util/__init__.py
ai_service_python_sdk-1.1.5.dist-info/METADATA
ai_service_python_sdk-1.1.5.dist-info/WHEEL
ai_service_python_sdk-1.1.5.dist-info/top_level.txt
ai_service_python_sdk-1.1.5.dist-info/RECORD
