Metadata-Version: 2.1
Name: ai_service_python_sdk
Version: 1.1.5
Summary: ai service python sdk
Home-page: 
Author-email: bruceding.jing@alibaba-inc.com
Keywords: ai service,Python SDK
Requires-Dist: urllib3 >=1.15
Requires-Dist: six >=1.10
Requires-Dist: certifi
Requires-Dist: python-dateutil
